csbschema/__init__.py
csbschema/validators.py
csbschema/command/__init__.py
csbschema/command/__main__.py
csbschema/command/validate.py
csbschema/data/CSB-schema-3_0_0-2023-03.json
csbschema/data/CSB-schema-3_0_0-2023-08.json
csbschema/data/CSB-schema-3_1_0-2023-03.json
csbschema/data/CSB-schema-3_1_0-2023-08.json
csbschema/data/CSB-schema-3_1_0-2024-04.json
csbschema/data/CSB-schema-3_2_0-BETA.json
csbschema/data/XYZ-CSB-schema-3_0_0-2023-03.json
csbschema/data/XYZ-CSB-schema-3_0_0-2023-08.json
csbschema/data/XYZ-CSB-schema-3_1_0-2023-08.json
csbschema/data/XYZ-CSB-schema-3_1_0-2024-04.json
csbschema/data/__init__.py
csbschema-1.1.2.dist-info/LICENSE.txt
csbschema-1.1.2.dist-info/METADATA
csbschema-1.1.2.dist-info/WHEEL
csbschema-1.1.2.dist-info/entry_points.txt
csbschema-1.1.2.dist-info/top_level.txt
csbschema-1.1.2.dist-info/RECORD
