Metadata-Version: 2.1
Name: csbschema
Version: 1.1.2
Summary: JSON Schema and validator for IHO B-12 Crowdsourced Bathymetry metadata and data
Author-email: Brian Miles <bmiles@ccom.unh.edu>, Brian Calder <brc@ccom.unh.edu>
Project-URL: Homepage, https://github.com/CCOMJHC/csbschema
Project-URL: Bug Tracker, https://github.com/CCOMJHC/csbschema/issues
Classifier: Programming Language :: Python :: 3
Classifier: License :: Other/Proprietary License
Classifier: Operating System :: OS Independent
Requires-Python: >=3.8
License-File: LICENSE.txt
Requires-Dist: jsonschema[format] ~=4.21.0
Provides-Extra: test
Requires-Dist: flake8 ; extra == 'test'
Requires-Dist: unittest-xml-reporting >=3.2.0 ; extra == 'test'
Requires-Dist: lxml >=4.6.5 ; extra == 'test'
Requires-Dist: pytest >=7.2.0 ; extra == 'test'
Requires-Dist: pytest-cov >=4.0.0 ; extra == 'test'
Requires-Dist: pytest-xdist >=3.0.2 ; extra == 'test'
